genice2_twist/__init__.py
genice2_twist/formats/__init__.py
genice2_twist/formats/twist.py
genice2_twist-2.0.dist-info/METADATA
genice2_twist-2.0.dist-info/WHEEL
genice2_twist-2.0.dist-info/entry_points.txt
genice2_twist-2.0.dist-info/top_level.txt
genice2_twist-2.0.dist-info/RECORD
