Metadata-Version: 2.1
Name: genice2-twist
Version: 2.0
Summary: Twist analysis plugin for GenIce.
Home-page: https://github.com/vitroid/genice-twist/
Author: Masakazu Matsumoto
Author-email: vitroid@gmail.com
License: MIT
Keywords: genice,chirality
Platform: UNKNOWN
Classifier: Development Status :: 4 - Beta
Classifier: Intended Audience :: Developers
Classifier: Programming Language :: Python
Classifier: Programming Language :: Python :: 3.6
Requires-Dist: genice2
Requires-Dist: genice2-svg (>=0.7)
Requires-Dist: twist-op (>=0.2)
Requires-Dist: sklearn
